jpeg_xl_float_with_nans/__init__.py
jpeg_xl_float_with_nans/jpeg_xl_float_with_nans.py
jpeg_xl_float_with_nans-0.0.4.dist-info/LICENSE
jpeg_xl_float_with_nans-0.0.4.dist-info/METADATA
jpeg_xl_float_with_nans-0.0.4.dist-info/WHEEL
jpeg_xl_float_with_nans-0.0.4.dist-info/top_level.txt
jpeg_xl_float_with_nans-0.0.4.dist-info/RECORD
