Metadata-Version: 2.1
Name: jpeg-xl-float-with-nans
Version: 0.0.4
Summary: JpegXlFloatWithNaNs is a codec for numcodecs for compressing image data in Zarr/Xarray
Author: Jacob Bieker, Jack Kelly
Author-email: info@openclimatefix.org
License: MIT
License-File: LICENSE
Requires-Dist: numpy
Requires-Dist: numcodecs
Requires-Dist: imagecodecs
